userpic.py
tiny_userpic-0.4.0.dist-info/METADATA
tiny_userpic-0.4.0.dist-info/WHEEL
tiny_userpic-0.4.0.dist-info/licenses/LICENSE
tiny_userpic-0.4.0.dist-info/RECORD
