Metadata-Version: 2.4
Name: tiny-userpic
Version: 0.4.0
Summary: Oversimplified Github-like userpic (avatar) generator
Project-URL: Homepage, https://github.com/shpaker/tiny-userpic/
Project-URL: Repository, https://github.com/shpaker/tiny-userpic/
Author-email: Aleksandr Shpak <shpaker@gmail.com>
License-Expression: MIT
License-File: LICENSE
Keywords: avatar,avatar-generator,userpic
Classifier: Development Status :: 4 - Beta
Classifier: Programming Language :: Python :: 3 :: Only
Classifier: Programming Language :: Python :: 3.10
Classifier: Programming Language :: Python :: 3.11
Classifier: Programming Language :: Python :: 3.12
Classifier: Programming Language :: Python :: 3.13
Classifier: Topic :: Software Development :: Libraries :: Python Modules
Requires-Python: >=3.10
Requires-Dist: pillow>=11.0
